{
    "compatibilities": [
        "EC2",
        "FARGATE"
    ],
    "containerDefinitions": [
        {
            "cpu": 0,
            "environment": [],
            "environmentFiles": [],
            "essential": true,
            "image": "019828916337.dkr.ecr.us-east-2.amazonaws.com/my-ecr-repo:latest",
            "logConfiguration": {
                "logDriver": "awslogs",
                "options": {
                    "awslogs-group": "/ecs/bohio-task",
                    "awslogs-create-group": "true",
                    "awslogs-region": "us-east-2",
                    "awslogs-stream-prefix": "ecs"
                },
                "secretOptions": []
            },
            "mountPoints": [],
            "name": "bohio-app",
            "portMappings": [
                {
                    "appProtocol": "http",
                    "containerPort": 80,
                    "hostPort": 80,
                    "name": "bohio-app-80-tcp",
                    "protocol": "tcp"
                }
            ],
            "systemControls": [],
            "ulimits": [],
            "volumesFrom": []
        }
    ],
    "cpu": "512",
    "enableFaultInjection": false,
    "executionRoleArn": "arn:aws:iam::019828916337:role/ecsTaskExecutionRole",
    "family": "bohio-task",
    "memory": "2048",
    "networkMode": "awsvpc",
    "placementConstraints": [],
    "registeredAt": "2025-09-17T23:57:14.745Z",
    "registeredBy": "arn:aws:iam::019828916337:root",
    "requiresAttributes": [
        {
            "name": "com.amazonaws.ecs.capability.logging-driver.awslogs"
        },
        {
            "name": "ecs.capability.execution-role-awslogs"
        },
        {
            "name": "com.amazonaws.ecs.capability.ecr-auth"
        },
        {
            "name": "com.amazonaws.ecs.capability.docker-remote-api.1.19"
        },
        {
            "name": "ecs.capability.execution-role-ecr-pull"
        },
        {
            "name": "com.amazonaws.ecs.capability.docker-remote-api.1.18"
        },
        {
            "name": "ecs.capability.task-eni"
        },
        {
            "name": "com.amazonaws.ecs.capability.docker-remote-api.1.29"
        }
    ],
    "requiresCompatibilities": [
        "FARGATE"
    ],
    "revision": 1,
    "runtimePlatform": {
        "cpuArchitecture": "ARM64",
        "operatingSystemFamily": "LINUX"
    },
    "status": "ACTIVE",
    "taskDefinitionArn": "arn:aws:ecs:us-east-2:019828916337:task-definition/bohio-task:1",
    "volumes": [],
    "tags": []
}